<?xml version="1.0" encoding="utf-8"?>
<doctrine-mapping xmlns="http://doctrine-project.org/schemas/orm/doctrine-mapping" xmlns:xsi="http://www.w3.org/2001/XMLSchema-instance" xsi:schemaLocation="http://doctrine-project.org/schemas/orm/doctrine-mapping http://doctrine-project.org/schemas/orm/doctrine-mapping.xsd">
  <entity name="AppBundle\Entity\Report" table="reports">
    <indexes>
      <index name="location_id" columns="location_id"/>
      <index name="technician_id" columns="technician_id"/>
    </indexes>
    <unique-constraints>
      <unique-constraint name="id_UNIQUE" columns="id"/>
    </unique-constraints>
    <id name="id" type="integer" column="id">
      <generator strategy="IDENTITY"/>
    </id>
    <field name="date" type="date" column="date" nullable="false"/>
    <field name="handled" type="boolean" column="handled" nullable="false">
      <options>
        <option name="default">0</option>
      </options>
    </field>
    <field name="actionId" type="integer" column="action_id" nullable="true">
      <options>
        <option name="unsigned"/>
      </options>
    </field>
    <many-to-one field="location" target-entity="Location" fetch="LAZY">
      <join-columns>
        <join-column name="location_id" referenced-column-name="id"/>
      </join-columns>
    </many-to-one>
    <many-to-one field="technician" target-entity="Technician" fetch="LAZY">
      <join-columns>
        <join-column name="technician_id" referenced-column-name="id"/>
      </join-columns>
    </many-to-one>
  </entity>
</doctrine-mapping>
